Cipher/__init__.py
Cipher/__main__.py
Cipher/_version.py
Cipher/conns/__init__.py
Cipher/conns/discord/__init__.py
Cipher/conns/discord/config.py
Cipher/conns/discord/config.pyi
Cipher/conns/discord/connection.py
Cipher/conns/discord/connection.pyi
Cipher/conns/discord/event.py
Cipher/conns/discord/event.pyi
Cipher/conns/discord/models.py
Cipher/conns/discord/models.pyi
Cipher/conns/irc/__init__.py
Cipher/conns/irc/config.py
Cipher/conns/irc/config.pyi
Cipher/conns/irc/connection.py
Cipher/conns/irc/connection.pyi
Cipher/conns/irc/event.py
Cipher/conns/irc/event.pyi
Cipher/conns/irc/models.py
Cipher/conns/irc/models.pyi
Cipher/conns/tg/__init__.py
Cipher/conns/tg/config.py
Cipher/conns/tg/config.pyi
Cipher/conns/tg/connection.py
Cipher/conns/tg/connection.pyi
Cipher/conns/tg/event.py
Cipher/conns/tg/event.pyi
Cipher/conns/tg/models.py
Cipher/conns/tg/models.pyi
Cipher/core/__init__.py
Cipher/core/cli.py
Cipher/core/config.py
Cipher/core/config.pyi
Cipher/core/connection.py
Cipher/core/connection.pyi
Cipher/core/constants.py
Cipher/core/core.py
Cipher/core/core.pyi
Cipher/core/event.py
Cipher/core/event.pyi
Cipher/core/models.py
Cipher/core/models.pyi
Cipher/core/plugin.py
Cipher/core/plugin.pyi
Cipher/core/utils.py
Cipher/core/utils.pyi
Cipher/plugins/__init__.py
Cipher/plugins/bridge.py
Cipher/plugins/bridge.pyi
Cipher/plugins/core.py
Cipher/plugins/core.pyi
Cipher/plugins/relay.py
Cipher/plugins/relay.pyi
Cipher_Bot-0.3.2.dist-info/DESCRIPTION.rst
Cipher_Bot-0.3.2.dist-info/METADATA
Cipher_Bot-0.3.2.dist-info/RECORD
Cipher_Bot-0.3.2.dist-info/WHEEL
Cipher_Bot-0.3.2.dist-info/dependency_links.txt
Cipher_Bot-0.3.2.dist-info/entry_points.txt
Cipher_Bot-0.3.2.dist-info/metadata.json
Cipher_Bot-0.3.2.dist-info/top_level.txt
