Metadata-Version: 2.0
Name: Cipher-Bot
Version: 0.3.2
Summary: A multi-platform chat bot framework.
Home-page: https://github.com/johnlage/Cipher
Author: John Lage
Author-email: me@johnlage.com
License: Apache Software License 2.0
Project-URL: Source, https://gitlab.com/johnlage/Cipher
Project-URL: Issues, https://gitlab.com/johnlage/Cipher/issues
Platform: UNKNOWN
Classifier: Development Status :: 3 - Alpha
Classifier: Intended Audience :: Other Audience
Classifier: License :: OSI Approved :: Apache Software License
Classifier: Natural Language :: English
Classifier: Operating System :: Unix
Classifier: Operating System :: POSIX
Classifier: Operating System :: Microsoft :: Windows
Classifier: Programming Language :: Python
Classifier: Programming Language :: Python :: 3
Classifier: Programming Language :: Python :: 3 :: Only
Classifier: Programming Language :: Python :: 3.6
Classifier: Programming Language :: Python :: Implementation :: CPython
Classifier: Topic :: Communications :: Chat
Classifier: Topic :: Communications :: Chat :: Internet Relay Chat
Requires-Python: ~=3.6
Requires-Dist: bottom
Requires-Dist: aiotg
Requires-Dist: discord.py
Requires-Dist: click
Requires-Dist: daiquiri
Requires-Dist: yarl (<1.0)
